clip_mmd/__init__.py
clip_mmd/calculation.py
clip_mmd/cli.py
clip_mmd/data.py
clip_mmd/logic.py
clip_mmd-0.0.2.dist-info/LICENSE
clip_mmd-0.0.2.dist-info/METADATA
clip_mmd-0.0.2.dist-info/WHEEL
clip_mmd-0.0.2.dist-info/entry_points.txt
clip_mmd-0.0.2.dist-info/top_level.txt
clip_mmd-0.0.2.dist-info/RECORD
