Metadata-Version: 2.1
Name: clip-mmd
Version: 0.0.2
Summary: CLIP Maximum Mean Discrepancy (CMMD) for evaluating generative models
Home-page: https://github.com/arrrr2/clip-mmd
Author: arr2
Author-email: whnahengyuan@gmail.com
License: Apache License 2.0
Classifier: Programming Language :: Python :: 3
Classifier: License :: OSI Approved :: Apache Software License
Classifier: Operating System :: OS Independent
License-File: LICENSE
Requires-Dist: torch
Requires-Dist: torchvision
Requires-Dist: numpy
Requires-Dist: scipy
Requires-Dist: scikit-image
Requires-Dist: tqdm
Requires-Dist: pillow
Requires-Dist: requests
